{"id": "i-mobile", "name": "i-mobile", "category": "advertising", "website_url": "https://www2.i-mobile.co.jp/en/index.aspx", "ghostery_id": null, "company_id": "i-mobile", "company_name": "i-mobile", "iab_vendor": null, "truste_type": null, "description": null, "truste_privacy_url": null, "privacy_url": null, "date_range": ["2019-02", "2019-02"], "overview": {"reach": 0.0009178005071965739, "site_reach_top10k": 80, "site_avg_frequency": 0.17459981515049888, "cookies": 0.3149348174125181, "bad_qs": 0.10584667260789062, "tracked": 0.3178765119231952, "https": 0.5394280827109507, "requests": 6.0904564489882835, "requests_tracking": 3.1953847731162246, "content_length": 11635.240586270866, "requests_failed": 2.889454678012827, "has_blocking": 0.0, "script": 0.9451374411902077, "iframe": 0.23361541002769942, "beacon": 0.0, "image": 0.23789782321616504, "stylesheet": 0.02324000003505147, "font": 0.0, "xhr": 0.19259818135454648, "plugin": 0.0, "media": 1.1391727327614687e-05, "referer_leaked": 0.3197815592470594, "referer_leaked_header": 0.3110607538344116, "referer_leaked_url": 0.0, "hosts": 1.0, "reach_rank": 571, "site_reach_rank": 402}, "reach_time_series": {"page": [0.0009178005071965739], "ts": ["2019-02"], "site": [80]}, "presence_by_category": [["Entertainment", 38.46153846153846], ["Adult", 30.76923076923077], ["News and Portals", 15.384615384615385], ["Business", 7.6923076923076925], ["Reference", 7.6923076923076925]]}