{"id": "ivcbrasil.org.br", "name": "IVC Brasil", "category": "site_analytics", "website_url": "https://ivcbrasil.org.br/#/home", "ghostery_id": null, "company_id": null, "company_name": null, "iab_vendor": null, "truste_type": null, "description": null, "truste_privacy_url": null, "privacy_url": null, "date_range": ["2018-10", "2019-02"], "overview": {"reach": 0.00033111879137005416, "site_reach_top10k": 9, "site_avg_frequency": 0.5797172041919078, "cookies": 0.9058920399895072, "bad_qs": 0.0, "tracked": 0.9058920399895072, "https": 0.9455172112273748, "requests": 63.60101333955133, "requests_tracking": 1.2624505717644545, "content_length": 2362.8239674720917, "requests_failed": 62.30367396310006, "has_blocking": 0.0, "script": 0.15717207341125264, "iframe": 0.0, "beacon": 0.0, "image": 0.9883072468837137, "stylesheet": 0.0, "font": 0.0, "xhr": 0.00030361324045197083, "plugin": 0.0, "media": 0.0, "referer_leaked": 0.9326585832677529, "referer_leaked_header": 0.9124768039484294, "referer_leaked_url": 0.0, "hosts": 1.0, "reach_rank": 829, "site_reach_rank": 967}, "reach_time_series": {"page": [0.00039416884026471135, 0.00020911329840616732, 0.00016217412068439058, 0.00028561725199634046, 0.00033111879137005416], "ts": ["2018-10", "2018-11", "2018-12", "2019-01", "2019-02"], "site": [8, 8, 7, 8, 9]}, "presence_by_category": [["News and Portals", 100.0]]}